tiledb/client/__init__.py
tiledb/client/array.py
tiledb/client/assets.py
tiledb/client/client.py
tiledb/client/cloudarray.py
tiledb/client/config.py
tiledb/client/files.py
tiledb/client/folders.py
tiledb/client/groups.py
tiledb/client/pager.py
tiledb/client/pool_manager_wrapper.py
tiledb/client/tasks.py
tiledb/client/teamspaces.py
tiledb/client/tiledb_cloud_error.py
tiledb/client/tokens.py
tiledb/client/udf.py
tiledb/client/version.py
tiledb/client/workspaces.py
tiledb/client/_common/__init__.py
tiledb/client/_common/_array_backed.py
tiledb/client/_common/functions.py
tiledb/client/_common/futures.py
tiledb/client/_common/json_safe.py
tiledb/client/_common/ordered.py
tiledb/client/_common/pickle_compat.py
tiledb/client/_common/testonly.py
tiledb/client/_common/trampoline.py
tiledb/client/_common/utils.py
tiledb/client/_common/visitor.py
tiledb/client/_common/api_v2/__init__.py
tiledb/client/_common/api_v2/api_client.py
tiledb/client/_common/api_v2/configuration.py
tiledb/client/_common/api_v2/exceptions.py
tiledb/client/_common/api_v2/rest.py
tiledb/client/_common/api_v2/api/__init__.py
tiledb/client/_common/api_v2/api/array_api.py
tiledb/client/_common/api_v2/api/files_api.py
tiledb/client/_common/api_v2/api/groups_api.py
tiledb/client/_common/api_v2/api/notebooks_api.py
tiledb/client/_common/api_v2/api/query_api.py
tiledb/client/_common/api_v2/api/user_api.py
tiledb/client/_common/api_v2/models/__init__.py
tiledb/client/_common/api_v2/models/access_credential.py
tiledb/client/_common/api_v2/models/access_credential_credential.py
tiledb/client/_common/api_v2/models/access_credential_role.py
tiledb/client/_common/api_v2/models/access_credential_token.py
tiledb/client/_common/api_v2/models/access_credential_type.py
tiledb/client/_common/api_v2/models/access_credentials_data.py
tiledb/client/_common/api_v2/models/activity_event_type.py
tiledb/client/_common/api_v2/models/array.py
tiledb/client/_common/api_v2/models/array_activity_log.py
tiledb_client-3.0a10.dist-info/licenses/LICENSE
tiledb_client-3.0a10.dist-info/METADATA
tiledb_client-3.0a10.dist-info/WHEEL
tiledb_client-3.0a10.dist-info/top_level.txt
tiledb_client-3.0a10.dist-info/RECORD
